RsAts1500c/RsAts1500c.py
RsAts1500c/__init__.py
RsAts1500c/enums.py
RsAts1500c/Implementations/In.py
RsAts1500c/Implementations/Out.py
RsAts1500c/Implementations/Utilities.py
RsAts1500c/Implementations/__init__.py
RsAts1500c/Implementations/In_/StepMovement.py
RsAts1500c/Implementations/In_/TriggerOutput.py
RsAts1500c/Implementations/In_/__init__.py
RsAts1500c/Implementations/Out_/StepMovement.py
RsAts1500c/Implementations/Out_/TriggerOutput.py
RsAts1500c/Implementations/Out_/__init__.py
RsAts1500c/Internal/Conversions.py
RsAts1500c/Internal/Instrument.py
RsAts1500c/Internal/InstrumentErrors.py
RsAts1500c/Internal/Utilities.py
RsAts1500c/Internal/__init__.py
RsAts1500c-1.0.0.1.dist-info/METADATA
RsAts1500c-1.0.0.1.dist-info/WHEEL
RsAts1500c-1.0.0.1.dist-info/top_level.txt
RsAts1500c-1.0.0.1.dist-info/RECORD
