Metadata-Version: 2.1
Name: RsAts1500c
Version: 1.0.0.1
Summary: ATS1500C Python instrument driver from Rohde & Schwarz
Home-page: UNKNOWN
Author: Rohde & Schwarz GmbH & Co. KG
Author-email: Customer.Support@rohde-schwarz.com
License: MIT
Platform: UNKNOWN
Classifier: License :: OSI Approved :: MIT License
Classifier: Programming Language :: Python :: 3.7
Requires-Dist: PyVisa
